wikitoolkit/__init__.py
wikitoolkit/api.py
wikitoolkit/clickstreams.py
wikitoolkit/links.py
wikitoolkit/pageviews.py
wikitoolkit/quality.py
wikitoolkit/redirects.py
wikitoolkit/revisions.py
wikitoolkit/tools.py
wikitoolkit/topics.py
wikitoolkit-0.0.10.dist-info/METADATA
wikitoolkit-0.0.10.dist-info/WHEEL
wikitoolkit-0.0.10.dist-info/top_level.txt
wikitoolkit-0.0.10.dist-info/RECORD
