Metadata-Version: 2.1
Name: wikitoolkit
Version: 0.0.10
Summary: A set of tools for extracting and working with Wikipedia API and dump data.
Author: Patrick Gildersleve
Author-email: <p.gildersleve@exeter.ac.uk>
Keywords: python,wikipedia,wikimedia,mediawiki,API,dump
Classifier: Development Status :: 3 - Alpha
Classifier: Intended Audience :: Education
Classifier: Programming Language :: Python :: 3
Classifier: Operating System :: MacOS :: MacOS X
Classifier: Operating System :: Microsoft :: Windows
Requires-Dist: mwapi
Requires-Dist: mwviews
